no3gwt/ZonalAnalysis.py
no3gwt/__init__.py
no3gwt/_version.py
no3gwt/config.py
no3gwt/convolution_scenarios.py
no3gwt/gis_attribute_utils.py
no3gwt/well_setup.py
no3gwt/tests/conftest.py
no3gwt/tests/test_gis_utils.py
no3gwt/tests/test_ml_models.py
no3gwt/tests/test_official_repo.py
no3gwt/tests/test_pull_data.py
no3gwt/tests/test_root_path.py
no3gwt/tests/hidden/__init__.py
no3gwt-1.1.2.dist-info/.ipynb_checkpoints/SOURCES-checkpoint.txt
no3gwt-1.1.2.dist-info/AUTHORS.rst
no3gwt-1.1.2.dist-info/LICENSE.md
no3gwt-1.1.2.dist-info/METADATA
no3gwt-1.1.2.dist-info/WHEEL
no3gwt-1.1.2.dist-info/top_level.txt
no3gwt-1.1.2.dist-info/RECORD
