Metadata-Version: 2.1
Name: no3gwt
Version: 1.1.2
Summary: Groundwater - Nitrate Decision Support Tool software for the state of Wisconsin
Author-email: Paul Juckem <pfjuckem@usgs.gov>, Laura Schachter <lschachter@usgs.gov>, Nick Corson-Dosch <ncorson-dosch@usgs.gov>, Christopher Green <ctgreen@usgs.gov>
License: License
Project-URL: documentation, https://doi-usgs.github.io/no3gwt/latest/
Project-URL: repository, https://code.usgs.gov/water/NDST/no3gwt
Keywords: nitrate,groundwater,hydrogeology
Classifier: Development Status :: 4 - Beta
Classifier: Intended Audience :: Science/Research
Classifier: Programming Language :: Python :: 3 :: Only
Classifier: Topic :: Scientific/Engineering :: Hydrology
Requires-Python: >=3.10
License-File: LICENSE.md
License-File: AUTHORS.rst
Requires-Dist: numpy
Requires-Dist: gdal
Requires-Dist: scikit-learn ==1.2.1
Requires-Dist: scipy
Requires-Dist: matplotlib
Requires-Dist: netcdf4
Requires-Dist: notebook
Requires-Dist: jupyter
Requires-Dist: jupyterlab
Requires-Dist: joblib
Requires-Dist: pytest
Requires-Dist: flopy
Requires-Dist: pandas
Requires-Dist: pip
Requires-Dist: proj
Requires-Dist: xarray
Requires-Dist: fiona
Requires-Dist: geopandas
Requires-Dist: rtree
Requires-Dist: pyproj
Requires-Dist: pyshp
Requires-Dist: rasterio
Requires-Dist: openpyxl
Provides-Extra: docs
Requires-Dist: matplotlib ; extra == 'docs'
Requires-Dist: modflow-export[optional] ; extra == 'docs'
Requires-Dist: ipython[kernel] ; extra == 'docs'
Requires-Dist: sphinx ; extra == 'docs'
Requires-Dist: numpydoc ; extra == 'docs'
Requires-Dist: nbsphinx ; extra == 'docs'
Requires-Dist: sphinx-copybutton ; extra == 'docs'
Requires-Dist: sphinx-rtd-theme ; extra == 'docs'
Provides-Extra: optional
Requires-Dist: descartes ; extra == 'optional'
Requires-Dist: hydrofunctions ; extra == 'optional'
Provides-Extra: test
Requires-Dist: codecov ; extra == 'test'
Requires-Dist: coverage ; extra == 'test'
Requires-Dist: pytest ; extra == 'test'
Requires-Dist: pytest-timeout ; extra == 'test'
